diffFx_pytorch/__init__.py
diffFx_pytorch/processors/__init__.py
diffFx_pytorch/processors/base.py
diffFx_pytorch/processors/base_utils.py
diffFx_pytorch/processors/core/__init__.py
diffFx_pytorch/processors/core/envelope.py
diffFx_pytorch/processors/core/fir.py
diffFx_pytorch/processors/core/iir.py
diffFx_pytorch/processors/core/midside.py
diffFx_pytorch/processors/core/phase.py
diffFx_pytorch/processors/core/utils.py
diffFx_pytorch/processors/delay/__init__.py
diffFx_pytorch/processors/delay/basic.py
diffFx_pytorch/processors/delay/multitap.py
diffFx_pytorch/processors/delay/pinpong.py
diffFx_pytorch/processors/distortion/__init__.py
diffFx_pytorch/processors/distortion/bitcrusher.py
diffFx_pytorch/processors/distortion/func.py
diffFx_pytorch/processors/dynamics/__init__.py
diffFx_pytorch/processors/dynamics/compressor.py
diffFx_pytorch/processors/dynamics/deesser.py
diffFx_pytorch/processors/dynamics/expander.py
diffFx_pytorch/processors/dynamics/limiter.py
diffFx_pytorch/processors/dynamics/noisegate.py
diffFx_pytorch/processors/eq/__init__.py
diffFx_pytorch/processors/eq/dynamicEQ.py
diffFx_pytorch/processors/eq/graphicEQ.py
diffFx_pytorch/processors/eq/parametricEQ.py
diffFx_pytorch/processors/eq/tonestack.py
diffFx_pytorch/processors/filters/__init__.py
diffFx_pytorch/processors/filters/biquad.py
diffFx_pytorch/processors/filters/dc.py
diffFx_pytorch/processors/filters/fir.py
diffFx_pytorch/processors/filters/linkwitzRiley.py
diffFx_pytorch/processors/gain/__init__.py
diffFx_pytorch/processors/gain/gain.py
diffFx_pytorch/processors/modulation/__init__.py
diffFx_pytorch/processors/modulation/chorus.py
diffFx_pytorch/processors/modulation/flanger.py
diffFx_pytorch/processors/modulation/phaser.py
diffFx_pytorch/processors/reverb/__init__.py
diffFx_pytorch/processors/reverb/noiseShape.py
diffFx_pytorch/processors/spatial/__init__.py
diffFx_pytorch/processors/spatial/enhancer.py
diffFx_pytorch/processors/spatial/panning.py
difffx_pytorch-0.0.5.dist-info/licenses/LICENSE
difffx_pytorch-0.0.5.dist-info/METADATA
difffx_pytorch-0.0.5.dist-info/WHEEL
difffx_pytorch-0.0.5.dist-info/top_level.txt
difffx_pytorch-0.0.5.dist-info/RECORD
