Metadata-Version: 2.4
Name: diffFx_pytorch
Version: 0.0.5
Summary: Differentiable audio effect processors in PyTorch.
Home-page: https://github.com/ytsrt66589/diffFx-pytorch
Author: Yen-Tung (Arthur) Yeh
Author-email: ytsrt66589@gmail.com
License: Apache License 2.0
Classifier: License :: OSI Approved :: Apache Software License
Classifier: Topic :: Multimedia :: Sound/Audio
Classifier: Topic :: Scientific/Engineering
Requires-Python: >=3.10.0
License-File: LICENSE
Requires-Dist: torch
Requires-Dist: numpy
Requires-Dist: torchaudio
Requires-Dist: torchlpc==0.6.0
Requires-Dist: torchcomp
Requires-Dist: scipy
Requires-Dist: numba-cuda==0.4.0
Requires-Dist: pynvjitlink-cu12
Provides-Extra: extra
Requires-Dist: matplotlib; extra == "extra"
Requires-Dist: librosa; extra == "extra"
Dynamic: home-page
Dynamic: license-file
Dynamic: requires-python
